code_index_mcp/__init__.py
code_index_mcp/__main__.py
code_index_mcp/constants.py
code_index_mcp/project_manager_cache.py
code_index_mcp/project_settings.py
code_index_mcp/request_context.py
code_index_mcp/server.py
code_index_mcp/indexing/__init__.py
code_index_mcp/indexing/deep_index_manager.py
code_index_mcp/indexing/index_provider.py
code_index_mcp/indexing/json_index_builder.py
code_index_mcp/indexing/qualified_names.py
code_index_mcp/indexing/shallow_index_manager.py
code_index_mcp/indexing/sqlite_index_builder.py
code_index_mcp/indexing/sqlite_index_manager.py
code_index_mcp/indexing/sqlite_store.py
code_index_mcp/indexing/models/__init__.py
code_index_mcp/indexing/models/file_info.py
code_index_mcp/indexing/models/symbol_info.py
code_index_mcp/indexing/strategies/__init__.py
code_index_mcp/indexing/strategies/base_strategy.py
code_index_mcp/indexing/strategies/csharp_strategy.py
code_index_mcp/indexing/strategies/fallback_strategy.py
code_index_mcp/indexing/strategies/go_strategy.py
code_index_mcp/indexing/strategies/java_strategy.py
code_index_mcp/indexing/strategies/javascript_strategy.py
code_index_mcp/indexing/strategies/kotlin_strategy.py
code_index_mcp/indexing/strategies/objective_c_strategy.py
code_index_mcp/indexing/strategies/python_strategy.py
code_index_mcp/indexing/strategies/strategy_factory.py
code_index_mcp/indexing/strategies/typescript_strategy.py
code_index_mcp/indexing/strategies/zig_strategy.py
code_index_mcp/middleware/__init__.py
code_index_mcp/middleware/project_context_middleware.py
code_index_mcp/search/__init__.py
code_index_mcp/search/ag.py
code_index_mcp/search/base.py
code_index_mcp/search/basic.py
code_index_mcp/search/grep.py
code_index_mcp/search/ripgrep.py
code_index_mcp/search/ugrep.py
code_index_mcp/services/__init__.py
code_index_mcp/services/base_service.py
code_index_mcp/services/code_intelligence_service.py
code_index_mcp/services/file_discovery_service.py
code_index_mcp/services/file_service.py
code_index_mcp-2.13.0.dist-info/licenses/LICENSE
code_index_mcp-2.13.0.dist-info/METADATA
code_index_mcp-2.13.0.dist-info/WHEEL
code_index_mcp-2.13.0.dist-info/entry_points.txt
code_index_mcp-2.13.0.dist-info/top_level.txt
code_index_mcp-2.13.0.dist-info/RECORD
